{
  "Author": "DOCTOR STRANGE",
  "Telegram": "https://t.me/jitendraunatti_github",
  "name": "Sony Live Matches API",
  "last_updated": "08:40:08 PM 10-05-2026",
  "app_settings": {
    "PROXY": "ON",
    "state_code": "MH",
    "MULTI_CDN": "OFF",
    "Debugging": "OFF",
    "SUB_TYPE": "FREEMIUM",
    "RECIVER": "OFF",
    "REALTIME": "OFF",
    "REPLACEMENT": "OFF",
    "FREEPREVIEW": "AUTO",
    "ALL_IN_ONE": "ON",
    "SERVER_STATUS": "NORMAL",
    "USAGE_GUIDE": []
  },
  "data": [
    {
      "contentId": 1090530079,
      "video_info": {
        "title": "New Zealand Women's Tour of England 2026",
        "shortDescription": "The opening ODI at Chester‑le‑Street kicks off England’s home season, featuring a youthful side led by new captain Charlie Dean returning after a long post‑World Cup break, while a confident New Zealand arrive buoyed by their 2–1 series win over South Africa and Amelia Kerr’s standout form. Who will take the lead? Tune in to catch all the action from the 1st ODI of New Zealand Women's Tour of England 2026, LIVE only on Sony LIV.",
        "longDescription": "The opening ODI at Chester‑le‑Street kicks off England’s home season, featuring a youthful side led by new captain Charlie Dean returning after a long post‑World Cup break, while a confident New Zealand arrive buoyed by their 2–1 series win over South Africa and Amelia Kerr’s standout form. Who will take the lead? Tune in to catch all the action from the 1st ODI of New Zealand Women's Tour of England 2026, LIVE only on Sony LIV.",
        "genres": [
          "Cricket"
        ],
        "episodeTitle": "1st ODI - 10 May 2026 "
      },
      "stream_info": {
        "Maximum_Video_Quality": "SDR",
        "dai_asset_key": "https://dai.google.com/ssai/event/jRQlKg2DQWa70jsLHUtxGA/master.m3u8",
        "broadcast_channel": "Sony Sports Ten 5",
        "audio_language_list": [
          {
            "lang_code": "ENG",
            "lang_label": "English"
          }
        ],
        "emfAttributes__audio_languages": "ENG",
        "platformVariants": {
          "assetType": "MASTER",
          "assetName": "VOD_FULL_HD",
          "videoType": "FULL_HD",
          "audioLanguages": [
            {
              "audioId": 1,
              "audioLanguageName": "ENG",
              "isPreferred": true,
              "audioLanguageLabel": "English"
            }
          ],
          "subtitlesLanguages": [],
          "videoUrl": "NA"
        }
      },
      "air_dates": {
        "contractStartDate": "10 May 2026, 03:00 PM",
        "contractEndDate": "11 May 2026, 04:00 AM",
        "originalAirDate": "10 May 2026, 03:30 PM"
      },
      "image_cdn": {
        "portrait_thumb": "https://origin-staticv2.sonyliv.com/videoasset_images/manage_file/1000017872/1778244698968296_EngW_vs_NZW_1odi_8may_live_portrait_thumb.jpg",
        "thumbnail": "https://origin-staticv2.sonyliv.com/videoasset_images/manage_file/1000017872/1778244788810296_EngW_vs_NZW_1odi_8may_landscape_thumb.jpg",
        "masthead_mobile_v1": null,
        "masthead_mobile_v2": "https://origin-staticv2.sonyliv.com/videoasset_images/manage_file/1000017890/177833233686386_England_Women_vs_New_Zealand_Women_2026_Match_masthead_mobile_v2_984x1182.jpg",
        "masthead_logo": "https://origin-staticv2.sonyliv.com/videoasset_images/manage_file/1000017890/177833233667186_England_Women_vs_New_Zealand_Women_2026_match_Masthead_logo_1st_ODI_Live.png",
        "circular_image": null,
        "image_600x900_clean": null,
        "landscape_thumb": "https://origin-staticv2.sonyliv.com/videoasset_images/manage_file/1000017872/1778244788810296_EngW_vs_NZW_1odi_8may_landscape_thumb.jpg"
      },
      "MULTIPLE_AUDIO_LINKS": [
        {
          "LANGUAGE": "English",
          "LANG_CODE": "ENG",
          "DATA": {
            "JITENDRAUNATTI": {
              "Device_Type": "LITE",
              "message": "success",
              "Playback_videoURL": "https://sonydaimenew.akamaized.net/hls/live/20000291/criclive1005/ENG/master.m3u8",
              "WIDEVINE": null,
              "STREAMING_TYPE": true,
              "audioLanguages": [
                {
                  "audioLanguageName": "ENG",
                  "audioLanguageLabel": "English"
                }
              ],
              "dai_asset_key": "https://dai.google.com/ssai/event/_wNibTTjRKGbTJkQbT7_mQ/master.m3u8",
              "Maximum_Video_Quality": "SDR",
              "Maximum_Resolution": "FULL_HD",
              "trailer_url": "",
              "systemTime": 1778421013290,
              "DOCTOR_STRANGE": 1778421010,
              "additionalDataJson": {
                "adServer": "GAM",
                "ad_stack": "DAI-IMA",
                "audioCodec": "AAC",
                "audio_quality": "STEREO",
                "enc_format": "HLS",
                "fps": 25,
                "isDaiKey": true,
                "partners": [
                  "ALL"
                ],
                "resolution": "HD",
                "videoCodec": "H264",
                "video_quality": "SDR"
              },
              "Status_code": 200,
              "content_type": "application/json; charset=utf-8",
              "auto_streams": "#EXTM3U\n#EXT-X-VERSION:3\n#EXT-X-STREAM-INF:BANDWIDTH=428552,AVERAGE-BANDWIDTH=428552,CODECS=\"avc1.42e015,mp4a.40.2\",PROGRAM-ID=1,RESOLUTION=426x240,FRAME-RATE=25.000\nhttps://sonydaimenew.akamaized.net/hls/live/20000291/criclive1005/ENG/hdntl=exp=1778507413~acl=%2f*~id=04960767078707344212907984572738~data=hdntl,20000291,criclive1005,ENG~hmac=66da3862553798fecd9f30862e39d111c79f61f9c708dea4853ed176b4800c66/master_200.m3u8?aka_me_session_id=AAAAAAAAAACV3gFqAAAAAJjntaDc5+YpaXFaF%2fhrgPZWxQpoIO9HH+xYX3n33GxOrqVaBg6EWvUO4c1jgF7snQsDDSWfF51N&aka_media_format_type=hls\n#EXT-X-STREAM-INF:BANDWIDTH=632904,AVERAGE-BANDWIDTH=632904,CODECS=\"avc1.4d401e,mp4a.40.2\",PROGRAM-ID=1,RESOLUTION=640x360,FRAME-RATE=25.000\nhttps://sonydaimenew.akamaized.net/hls/live/20000291/criclive1005/ENG/hdntl=exp=1778507413~acl=%2f*~id=04960767078707344212907984572738~data=hdntl,20000291,criclive1005,ENG~hmac=66da3862553798fecd9f30862e39d111c79f61f9c708dea4853ed176b4800c66/master_400.m3u8?aka_me_session_id=AAAAAAAAAACV3gFqAAAAAJjntaDc5+YpaXFaF%2fhrgPZWxQpoIO9HH+xYX3n33GxOrqVaBg6EWvUO4c1jgF7snQsDDSWfF51N&aka_media_format_type=hls\n#EXT-X-STREAM-INF:BANDWIDTH=833160,AVERAGE-BANDWIDTH=833160,CODECS=\"avc1.4d401e,mp4a.40.2\",PROGRAM-ID=1,RESOLUTION=640x360,FRAME-RATE=25.000\nhttps://sonydaimenew.akamaized.net/hls/live/20000291/criclive1005/ENG/hdntl=exp=1778507413~acl=%2f*~id=04960767078707344212907984572738~data=hdntl,20000291,criclive1005,ENG~hmac=66da3862553798fecd9f30862e39d111c79f61f9c708dea4853ed176b4800c66/master_500.m3u8?aka_me_session_id=AAAAAAAAAACV3gFqAAAAAJjntaDc5+YpaXFaF%2fhrgPZWxQpoIO9HH+xYX3n33GxOrqVaBg6EWvUO4c1jgF7snQsDDSWfF51N&aka_media_format_type=hls\n#EXT-X-STREAM-INF:BANDWIDTH=837256,AVERAGE-BANDWIDTH=837256,CODECS=\"avc1.64001f,mp4a.40.2\",PROGRAM-ID=1,RESOLUTION=854x480,FRAME-RATE=25.000\nhttps://sonydaimenew.akamaized.net/hls/live/20000291/criclive1005/ENG/hdntl=exp=1778507413~acl=%2f*~id=04960767078707344212907984572738~data=hdntl,20000291,criclive1005,ENG~hmac=66da3862553798fecd9f30862e39d111c79f61f9c708dea4853ed176b4800c66/master_600.m3u8?aka_me_session_id=AAAAAAAAAACV3gFqAAAAAJjntaDc5+YpaXFaF%2fhrgPZWxQpoIO9HH+xYX3n33GxOrqVaBg6EWvUO4c1jgF7snQsDDSWfF51N&aka_media_format_type=hls\n#EXT-X-STREAM-INF:BANDWIDTH=1344040,AVERAGE-BANDWIDTH=1344040,CODECS=\"avc1.64001f,mp4a.40.2\",PROGRAM-ID=1,RESOLUTION=960x540,FRAME-RATE=25.000\nhttps://sonydaimenew.akamaized.net/hls/live/20000291/criclive1005/ENG/hdntl=exp=1778507413~acl=%2f*~id=04960767078707344212907984572738~data=hdntl,20000291,criclive1005,ENG~hmac=66da3862553798fecd9f30862e39d111c79f61f9c708dea4853ed176b4800c66/master_1000.m3u8?aka_me_session_id=AAAAAAAAAACV3gFqAAAAAJjntaDc5+YpaXFaF%2fhrgPZWxQpoIO9HH+xYX3n33GxOrqVaBg6EWvUO4c1jgF7snQsDDSWfF51N&aka_media_format_type=hls\n#EXT-X-STREAM-INF:BANDWIDTH=1552456,AVERAGE-BANDWIDTH=1552456,CODECS=\"avc1.640020,mp4a.40.2\",PROGRAM-ID=1,RESOLUTION=1280x720,FRAME-RATE=25.000\nhttps://sonydaimenew.akamaized.net/hls/live/20000291/criclive1005/ENG/hdntl=exp=1778507413~acl=%2f*~id=04960767078707344212907984572738~data=hdntl,20000291,criclive1005,ENG~hmac=66da3862553798fecd9f30862e39d111c79f61f9c708dea4853ed176b4800c66/master_1300.m3u8?aka_me_session_id=AAAAAAAAAACV3gFqAAAAAJjntaDc5+YpaXFaF%2fhrgPZWxQpoIO9HH+xYX3n33GxOrqVaBg6EWvUO4c1jgF7snQsDDSWfF51N&aka_media_format_type=hls\n#EXT-X-STREAM-INF:BANDWIDTH=2365768,AVERAGE-BANDWIDTH=2365768,CODECS=\"avc1.640020,mp4a.40.2\",PROGRAM-ID=1,RESOLUTION=1280x720,FRAME-RATE=25.000\nhttps://sonydaimenew.akamaized.net/hls/live/20000291/criclive1005/ENG/hdntl=exp=1778507413~acl=%2f*~id=04960767078707344212907984572738~data=hdntl,20000291,criclive1005,ENG~hmac=66da3862553798fecd9f30862e39d111c79f61f9c708dea4853ed176b4800c66/master_2000.m3u8?aka_me_session_id=AAAAAAAAAACV3gFqAAAAAJjntaDc5+YpaXFaF%2fhrgPZWxQpoIO9HH+xYX3n33GxOrqVaBg6EWvUO4c1jgF7snQsDDSWfF51N&aka_media_format_type=hls\n#EXT-X-STREAM-INF:BANDWIDTH=2365768,AVERAGE-BANDWIDTH=2365768,CODECS=\"avc1.64002a,mp4a.40.2\",PROGRAM-ID=1,RESOLUTION=1920x1080,FRAME-RATE=25.000\nhttps://sonydaimenew.akamaized.net/hls/live/20000291/criclive1005/ENG/hdntl=exp=1778507413~acl=%2f*~id=04960767078707344212907984572738~data=hdntl,20000291,criclive1005,ENG~hmac=66da3862553798fecd9f30862e39d111c79f61f9c708dea4853ed176b4800c66/master_2200.m3u8?aka_me_session_id=AAAAAAAAAACV3gFqAAAAAJjntaDc5+YpaXFaF%2fhrgPZWxQpoIO9HH+xYX3n33GxOrqVaBg6EWvUO4c1jgF7snQsDDSWfF51N&aka_media_format_type=hls\n#EXT-X-STREAM-INF:BANDWIDTH=3591848,AVERAGE-BANDWIDTH=3591848,CODECS=\"avc1.64002a,mp4a.40.2\",PROGRAM-ID=1,RESOLUTION=1920x1080,FRAME-RATE=25.000\nhttps://sonydaimenew.akamaized.net/hls/live/20000291/criclive1005/ENG/hdntl=exp=1778507413~acl=%2f*~id=04960767078707344212907984572738~data=hdntl,20000291,criclive1005,ENG~hmac=66da3862553798fecd9f30862e39d111c79f61f9c708dea4853ed176b4800c66/master_3200.m3u8?aka_me_session_id=AAAAAAAAAACV3gFqAAAAAJjntaDc5+YpaXFaF%2fhrgPZWxQpoIO9HH+xYX3n33GxOrqVaBg6EWvUO4c1jgF7snQsDDSWfF51N&aka_media_format_type=hls\n#EXT-X-STREAM-INF:BANDWIDTH=4963232,AVERAGE-BANDWIDTH=4963232,CODECS=\"avc1.64002a,mp4a.40.2\",PROGRAM-ID=1,RESOLUTION=1920x1080,FRAME-RATE=50.000\nhttps://sonydaimenew.akamaized.net/hls/live/20000291/criclive1005/ENG/hdntl=exp=1778507413~acl=%2f*~id=04960767078707344212907984572738~data=hdntl,20000291,criclive1005,ENG~hmac=66da3862553798fecd9f30862e39d111c79f61f9c708dea4853ed176b4800c66/master_4500.m3u8?aka_me_session_id=AAAAAAAAAACV3gFqAAAAAJjntaDc5+YpaXFaF%2fhrgPZWxQpoIO9HH+xYX3n33GxOrqVaBg6EWvUO4c1jgF7snQsDDSWfF51N&aka_media_format_type=hls",
              "date": "Sunday 10th of May 2026 07:20:10 PM"
            }
          }
        }
      ]
    },
    {
      "contentId": 1090530051,
      "video_info": {
        "title": "Bundesliga 2025-26",
        "shortDescription": "Hamburger SV host Freiburg in a Bundesliga clash, with both sides eager to secure crucial points as the season enters its decisive phase. Freiburg will look to rely on their attacking discipline and consistency, while Hamburg aim to make home advantage count in what promises to be a closely fought encounter. Catch all the action from Bundesliga 2025-26, LIVE on Sony LIV.",
        "longDescription": "Hamburger SV host Freiburg in a Bundesliga clash, with both sides eager to secure crucial points as the season enters its decisive phase. Freiburg will look to rely on their attacking discipline and consistency, while Hamburg aim to make home advantage count in what promises to be a closely fought encounter. Catch all the action from Bundesliga 2025-26, LIVE on Sony LIV.",
        "genres": [
          "Football"
        ],
        "episodeTitle": "Hamburger SV vs Freiburg - MD 33 - 10 May 2026"
      },
      "stream_info": {
        "Maximum_Video_Quality": "SDR",
        "dai_asset_key": "https://dai.google.com/ssai/event/AmQPWgDqQUWpYQBuiuFZhw/master.m3u8",
        "broadcast_channel": "Sony Sports Ten 2",
        "audio_language_list": [
          {
            "lang_code": "ENG",
            "lang_label": "English"
          }
        ],
        "emfAttributes__audio_languages": "ENG",
        "platformVariants": {
          "assetType": "MASTER",
          "assetName": "VOD_FULL_HD",
          "videoType": "FULL_HD",
          "audioLanguages": [
            {
              "audioId": 1,
              "audioLanguageName": "ENG",
              "isPreferred": true,
              "audioLanguageLabel": "English"
            }
          ],
          "subtitlesLanguages": [],
          "videoUrl": "NA"
        }
      },
      "air_dates": {
        "contractStartDate": "10 May 2026, 06:20 PM",
        "contractEndDate": "10 May 2026, 11:20 PM",
        "originalAirDate": "10 May 2026, 06:50 PM"
      },
      "image_cdn": {
        "portrait_thumb": "https://origin-staticv2.sonyliv.com/videoasset_images/manage_file/1000017704/1777446987258341_Bundesliga_2025-26_MD-33_Hamburger-vs-SC-Freiburg_portrait_thumb.jpg",
        "thumbnail": "https://origin-staticv2.sonyliv.com/videoasset_images/manage_file/1000017704/1777447009894341_Bundesliga_2025-26_MD-33_Hamburger-vs-SC-Freiburg_landscape_thumb.jpg",
        "masthead_mobile_v1": null,
        "masthead_mobile_v2": null,
        "masthead_logo": "https://origin-staticv2.sonyliv.com/videoasset_images/manage_file/1000000507/1742306648095993_EuropeanQualifiers2025_GENERIC_Masthead_logo_LIVE.png",
        "circular_image": null,
        "image_600x900_clean": null,
        "landscape_thumb": "https://origin-staticv2.sonyliv.com/videoasset_images/manage_file/1000017704/1777447009894341_Bundesliga_2025-26_MD-33_Hamburger-vs-SC-Freiburg_landscape_thumb.jpg"
      },
      "MULTIPLE_AUDIO_LINKS": [
        {
          "LANGUAGE": "English",
          "LANG_CODE": "ENG",
          "DATA": {
            "JITENDRAUNATTI": {
              "Device_Type": "LITE",
              "message": "success",
              "Playback_videoURL": "https://sonydaimenew.akamaized.net/hls/live/2094589/Bliga_Ha1005/ENG/master.m3u8",
              "WIDEVINE": null,
              "STREAMING_TYPE": true,
              "audioLanguages": [
                {
                  "audioLanguageName": "ENG",
                  "audioLanguageLabel": "English"
                }
              ],
              "dai_asset_key": "https://dai.google.com/ssai/event/ik9hvNsSRdW1q6su6Tysyg/master.m3u8",
              "Maximum_Video_Quality": "SDR",
              "Maximum_Resolution": "FULL_HD",
              "trailer_url": "",
              "systemTime": 1778417412346,
              "DOCTOR_STRANGE": 1778417409,
              "additionalDataJson": {
                "adServer": "GAM",
                "ad_stack": "DAI-IMA",
                "audioCodec": "AAC",
                "audio_quality": "STEREO",
                "enc_format": "HLS",
                "fps": 25,
                "isDaiKey": true,
                "partners": [
                  "ALL"
                ],
                "resolution": "HD",
                "videoCodec": "H264",
                "video_quality": "SDR"
              },
              "Status_code": 200,
              "content_type": "application/json; charset=utf-8",
              "auto_streams": "#EXTM3U\n#EXT-X-VERSION:3\n#EXT-X-STREAM-INF:BANDWIDTH=428552,AVERAGE-BANDWIDTH=428552,CODECS=\"avc1.42e015,mp4a.40.2\",PROGRAM-ID=1,RESOLUTION=426x240,FRAME-RATE=25.000\nhttps://sonydaimenew.akamaized.net/hls/live/2094589/Bliga_Ha1005/ENG/hdntl=exp=1778503812~acl=%2f*~id=13922362406065226171988165170857~data=hdntl,2094589,Bliga_Ha1005,ENG~hmac=effe68cec52b1640c4a99c71773eb1d4bd16a6e36e76e8c0b16c981bc8e0ca04/master_200.m3u8?aka_me_session_id=AAAAAAAAAACE0AFqAAAAALBmj9fvkfYLU3gGr5LbKKEdTQ4tBhAcGps6QRc5EpSL4SJhdt58Nb8wzYQitdgTbrya7TMLyqmJ&aka_media_format_type=hls\n#EXT-X-STREAM-INF:BANDWIDTH=632904,AVERAGE-BANDWIDTH=632904,CODECS=\"avc1.4d401e,mp4a.40.2\",PROGRAM-ID=1,RESOLUTION=640x360,FRAME-RATE=25.000\nhttps://sonydaimenew.akamaized.net/hls/live/2094589/Bliga_Ha1005/ENG/hdntl=exp=1778503812~acl=%2f*~id=13922362406065226171988165170857~data=hdntl,2094589,Bliga_Ha1005,ENG~hmac=effe68cec52b1640c4a99c71773eb1d4bd16a6e36e76e8c0b16c981bc8e0ca04/master_400.m3u8?aka_me_session_id=AAAAAAAAAACE0AFqAAAAALBmj9fvkfYLU3gGr5LbKKEdTQ4tBhAcGps6QRc5EpSL4SJhdt58Nb8wzYQitdgTbrya7TMLyqmJ&aka_media_format_type=hls\n#EXT-X-STREAM-INF:BANDWIDTH=833160,AVERAGE-BANDWIDTH=833160,CODECS=\"avc1.4d401e,mp4a.40.2\",PROGRAM-ID=1,RESOLUTION=640x360,FRAME-RATE=25.000\nhttps://sonydaimenew.akamaized.net/hls/live/2094589/Bliga_Ha1005/ENG/hdntl=exp=1778503812~acl=%2f*~id=13922362406065226171988165170857~data=hdntl,2094589,Bliga_Ha1005,ENG~hmac=effe68cec52b1640c4a99c71773eb1d4bd16a6e36e76e8c0b16c981bc8e0ca04/master_500.m3u8?aka_me_session_id=AAAAAAAAAACE0AFqAAAAALBmj9fvkfYLU3gGr5LbKKEdTQ4tBhAcGps6QRc5EpSL4SJhdt58Nb8wzYQitdgTbrya7TMLyqmJ&aka_media_format_type=hls\n#EXT-X-STREAM-INF:BANDWIDTH=837256,AVERAGE-BANDWIDTH=837256,CODECS=\"avc1.64001f,mp4a.40.2\",PROGRAM-ID=1,RESOLUTION=854x480,FRAME-RATE=25.000\nhttps://sonydaimenew.akamaized.net/hls/live/2094589/Bliga_Ha1005/ENG/hdntl=exp=1778503812~acl=%2f*~id=13922362406065226171988165170857~data=hdntl,2094589,Bliga_Ha1005,ENG~hmac=effe68cec52b1640c4a99c71773eb1d4bd16a6e36e76e8c0b16c981bc8e0ca04/master_600.m3u8?aka_me_session_id=AAAAAAAAAACE0AFqAAAAALBmj9fvkfYLU3gGr5LbKKEdTQ4tBhAcGps6QRc5EpSL4SJhdt58Nb8wzYQitdgTbrya7TMLyqmJ&aka_media_format_type=hls\n#EXT-X-STREAM-INF:BANDWIDTH=1344040,AVERAGE-BANDWIDTH=1344040,CODECS=\"avc1.64001f,mp4a.40.2\",PROGRAM-ID=1,RESOLUTION=960x540,FRAME-RATE=25.000\nhttps://sonydaimenew.akamaized.net/hls/live/2094589/Bliga_Ha1005/ENG/hdntl=exp=1778503812~acl=%2f*~id=13922362406065226171988165170857~data=hdntl,2094589,Bliga_Ha1005,ENG~hmac=effe68cec52b1640c4a99c71773eb1d4bd16a6e36e76e8c0b16c981bc8e0ca04/master_1000.m3u8?aka_me_session_id=AAAAAAAAAACE0AFqAAAAALBmj9fvkfYLU3gGr5LbKKEdTQ4tBhAcGps6QRc5EpSL4SJhdt58Nb8wzYQitdgTbrya7TMLyqmJ&aka_media_format_type=hls\n#EXT-X-STREAM-INF:BANDWIDTH=1552456,AVERAGE-BANDWIDTH=1552456,CODECS=\"avc1.640020,mp4a.40.2\",PROGRAM-ID=1,RESOLUTION=1280x720,FRAME-RATE=25.000\nhttps://sonydaimenew.akamaized.net/hls/live/2094589/Bliga_Ha1005/ENG/hdntl=exp=1778503812~acl=%2f*~id=13922362406065226171988165170857~data=hdntl,2094589,Bliga_Ha1005,ENG~hmac=effe68cec52b1640c4a99c71773eb1d4bd16a6e36e76e8c0b16c981bc8e0ca04/master_1300.m3u8?aka_me_session_id=AAAAAAAAAACE0AFqAAAAALBmj9fvkfYLU3gGr5LbKKEdTQ4tBhAcGps6QRc5EpSL4SJhdt58Nb8wzYQitdgTbrya7TMLyqmJ&aka_media_format_type=hls\n#EXT-X-STREAM-INF:BANDWIDTH=2365768,AVERAGE-BANDWIDTH=2365768,CODECS=\"avc1.640020,mp4a.40.2\",PROGRAM-ID=1,RESOLUTION=1280x720,FRAME-RATE=25.000\nhttps://sonydaimenew.akamaized.net/hls/live/2094589/Bliga_Ha1005/ENG/hdntl=exp=1778503812~acl=%2f*~id=13922362406065226171988165170857~data=hdntl,2094589,Bliga_Ha1005,ENG~hmac=effe68cec52b1640c4a99c71773eb1d4bd16a6e36e76e8c0b16c981bc8e0ca04/master_2000.m3u8?aka_me_session_id=AAAAAAAAAACE0AFqAAAAALBmj9fvkfYLU3gGr5LbKKEdTQ4tBhAcGps6QRc5EpSL4SJhdt58Nb8wzYQitdgTbrya7TMLyqmJ&aka_media_format_type=hls\n#EXT-X-STREAM-INF:BANDWIDTH=2365768,AVERAGE-BANDWIDTH=2365768,CODECS=\"avc1.64002a,mp4a.40.2\",PROGRAM-ID=1,RESOLUTION=1920x1080,FRAME-RATE=25.000\nhttps://sonydaimenew.akamaized.net/hls/live/2094589/Bliga_Ha1005/ENG/hdntl=exp=1778503812~acl=%2f*~id=13922362406065226171988165170857~data=hdntl,2094589,Bliga_Ha1005,ENG~hmac=effe68cec52b1640c4a99c71773eb1d4bd16a6e36e76e8c0b16c981bc8e0ca04/master_2200.m3u8?aka_me_session_id=AAAAAAAAAACE0AFqAAAAALBmj9fvkfYLU3gGr5LbKKEdTQ4tBhAcGps6QRc5EpSL4SJhdt58Nb8wzYQitdgTbrya7TMLyqmJ&aka_media_format_type=hls\n#EXT-X-STREAM-INF:BANDWIDTH=3591848,AVERAGE-BANDWIDTH=3591848,CODECS=\"avc1.64002a,mp4a.40.2\",PROGRAM-ID=1,RESOLUTION=1920x1080,FRAME-RATE=25.000\nhttps://sonydaimenew.akamaized.net/hls/live/2094589/Bliga_Ha1005/ENG/hdntl=exp=1778503812~acl=%2f*~id=13922362406065226171988165170857~data=hdntl,2094589,Bliga_Ha1005,ENG~hmac=effe68cec52b1640c4a99c71773eb1d4bd16a6e36e76e8c0b16c981bc8e0ca04/master_3200.m3u8?aka_me_session_id=AAAAAAAAAACE0AFqAAAAALBmj9fvkfYLU3gGr5LbKKEdTQ4tBhAcGps6QRc5EpSL4SJhdt58Nb8wzYQitdgTbrya7TMLyqmJ&aka_media_format_type=hls\n#EXT-X-STREAM-INF:BANDWIDTH=4963232,AVERAGE-BANDWIDTH=4963232,CODECS=\"avc1.64002a,mp4a.40.2\",PROGRAM-ID=1,RESOLUTION=1920x1080,FRAME-RATE=50.000\nhttps://sonydaimenew.akamaized.net/hls/live/2094589/Bliga_Ha1005/ENG/hdntl=exp=1778503812~acl=%2f*~id=13922362406065226171988165170857~data=hdntl,2094589,Bliga_Ha1005,ENG~hmac=effe68cec52b1640c4a99c71773eb1d4bd16a6e36e76e8c0b16c981bc8e0ca04/master_4500.m3u8?aka_me_session_id=AAAAAAAAAACE0AFqAAAAALBmj9fvkfYLU3gGr5LbKKEdTQ4tBhAcGps6QRc5EpSL4SJhdt58Nb8wzYQitdgTbrya7TMLyqmJ&aka_media_format_type=hls",
              "date": "Sunday 10th of May 2026 06:20:09 PM"
            }
          }
        }
      ]
    },
    {
      "contentId": 1090530050,
      "video_info": {
        "title": "Bundesliga 2025-26",
        "shortDescription": "FC Koln welcome Heidenheim in a Bundesliga encounter, with both teams aiming to finish the season strongly and climb the standings. Koln will look to control proceedings at home, while Heidenheim seek a determined performance to challenge their hosts in an important clash. Catch all the action from Bundesliga 2025-26, LIVE on Sony LIV.",
        "longDescription": "FC Koln welcome Heidenheim in a Bundesliga encounter, with both teams aiming to finish the season strongly and climb the standings. Koln will look to control proceedings at home, while Heidenheim seek a determined performance to challenge their hosts in an important clash. Catch all the action from Bundesliga 2025-26, LIVE on Sony LIV.",
        "genres": [
          "Football"
        ],
        "episodeTitle": "FC Koln vs Heidenheim - MD 33 - 10 May 2026"
      },
      "stream_info": {
        "Maximum_Video_Quality": "SDR",
        "dai_asset_key": "https://dai.google.com/ssai/event/4G_G6zLURAiPOM4qZQcSTg/master.m3u8",
        "broadcast_channel": "Sony Sports Ten 2",
        "audio_language_list": [
          {
            "lang_code": "ENG",
            "lang_label": "English"
          }
        ],
        "emfAttributes__audio_languages": "ENG",
        "platformVariants": {
          "assetType": "MASTER",
          "assetName": "VOD_FULL_HD",
          "videoType": "FULL_HD",
          "audioLanguages": [
            {
              "audioId": 1,
              "audioLanguageName": "ENG",
              "isPreferred": true,
              "audioLanguageLabel": "English"
            }
          ],
          "subtitlesLanguages": [],
          "videoUrl": "NA"
        }
      },
      "air_dates": {
        "contractStartDate": "10 May 2026, 08:20 PM",
        "contractEndDate": "11 May 2026, 01:20 AM",
        "originalAirDate": "10 May 2026, 08:50 PM"
      },
      "image_cdn": {
        "portrait_thumb": "https://origin-staticv2.sonyliv.com/videoasset_images/manage_file/1000017704/1777452272735341_Bundesliga_2025-26_MD-33_Koln-vs-Heidenheim_portrait_thumb.jpg",
        "thumbnail": "https://origin-staticv2.sonyliv.com/videoasset_images/manage_file/1000017704/1777452284105341_Bundesliga_2025-26_MD-33_Koln-vs-Heidenheim_landscape_thumb.jpg",
        "masthead_mobile_v1": null,
        "masthead_mobile_v2": null,
        "masthead_logo": "https://origin-staticv2.sonyliv.com/videoasset_images/manage_file/1000000507/1742306648095993_EuropeanQualifiers2025_GENERIC_Masthead_logo_LIVE.png",
        "circular_image": null,
        "image_600x900_clean": null,
        "landscape_thumb": "https://origin-staticv2.sonyliv.com/videoasset_images/manage_file/1000017704/1777452284105341_Bundesliga_2025-26_MD-33_Koln-vs-Heidenheim_landscape_thumb.jpg"
      },
      "MULTIPLE_AUDIO_LINKS": [
        {
          "LANGUAGE": "English",
          "LANG_CODE": "ENG",
          "DATA": {
            "JITENDRAUNATTI": {
              "Device_Type": "LITE",
              "message": "success",
              "Playback_videoURL": "https://sonydaimenew.akamaized.net/hls/live/2005445/Bliga_FC1005/ENG/master.m3u8",
              "WIDEVINE": null,
              "STREAMING_TYPE": true,
              "audioLanguages": [
                {
                  "audioLanguageName": "ENG",
                  "audioLanguageLabel": "English"
                }
              ],
              "dai_asset_key": "https://dai.google.com/ssai/event/RTTpbIJBQVGaU86ZLdcz8Q/master.m3u8",
              "Maximum_Video_Quality": "SDR",
              "Maximum_Resolution": "FULL_HD",
              "trailer_url": "",
              "systemTime": 1778424610462,
              "DOCTOR_STRANGE": 1778424609,
              "additionalDataJson": {
                "adServer": "GAM",
                "ad_stack": "DAI-IMA",
                "audioCodec": "AAC",
                "audio_quality": "STEREO",
                "enc_format": "HLS",
                "fps": 25,
                "isDaiKey": true,
                "partners": [
                  "ALL"
                ],
                "resolution": "HD",
                "videoCodec": "H264",
                "video_quality": "SDR"
              },
              "Status_code": 200,
              "content_type": "application/json; charset=utf-8",
              "auto_streams": "#EXTM3U\n#EXT-X-VERSION:3\n#EXT-X-STREAM-INF:BANDWIDTH=428552,AVERAGE-BANDWIDTH=428552,CODECS=\"avc1.42e015,mp4a.40.2\",PROGRAM-ID=1,RESOLUTION=426x240,FRAME-RATE=25.000\nhttps://sonydaimenew.akamaized.net/hls/live/2005445/Bliga_FC1005/ENG/hdntl=exp=1778511011~acl=%2f*~id=22255612131139629834187303491070~data=hdntl,2005445,Bliga_FC1005,ENG~hmac=a353b054bdca675af7dc00273b8a322afd7b8a50b4b52001bf4abafe6dff2794/master_200.m3u8?aka_me_session_id=AAAAAAAAAACj7AFqAAAAALWAShFhxbld0iKu%2flMDzaB%2f+x18VXK82%2f82gPnLtsUlMesCnn%2f6DsgYOh0pKE%2fCrSELKMoeRCA7&aka_media_format_type=hls\n#EXT-X-STREAM-INF:BANDWIDTH=632904,AVERAGE-BANDWIDTH=632904,CODECS=\"avc1.4d401e,mp4a.40.2\",PROGRAM-ID=1,RESOLUTION=640x360,FRAME-RATE=25.000\nhttps://sonydaimenew.akamaized.net/hls/live/2005445/Bliga_FC1005/ENG/hdntl=exp=1778511011~acl=%2f*~id=22255612131139629834187303491070~data=hdntl,2005445,Bliga_FC1005,ENG~hmac=a353b054bdca675af7dc00273b8a322afd7b8a50b4b52001bf4abafe6dff2794/master_400.m3u8?aka_me_session_id=AAAAAAAAAACj7AFqAAAAALWAShFhxbld0iKu%2flMDzaB%2f+x18VXK82%2f82gPnLtsUlMesCnn%2f6DsgYOh0pKE%2fCrSELKMoeRCA7&aka_media_format_type=hls\n#EXT-X-STREAM-INF:BANDWIDTH=833160,AVERAGE-BANDWIDTH=833160,CODECS=\"avc1.4d401e,mp4a.40.2\",PROGRAM-ID=1,RESOLUTION=640x360,FRAME-RATE=25.000\nhttps://sonydaimenew.akamaized.net/hls/live/2005445/Bliga_FC1005/ENG/hdntl=exp=1778511011~acl=%2f*~id=22255612131139629834187303491070~data=hdntl,2005445,Bliga_FC1005,ENG~hmac=a353b054bdca675af7dc00273b8a322afd7b8a50b4b52001bf4abafe6dff2794/master_500.m3u8?aka_me_session_id=AAAAAAAAAACj7AFqAAAAALWAShFhxbld0iKu%2flMDzaB%2f+x18VXK82%2f82gPnLtsUlMesCnn%2f6DsgYOh0pKE%2fCrSELKMoeRCA7&aka_media_format_type=hls\n#EXT-X-STREAM-INF:BANDWIDTH=837256,AVERAGE-BANDWIDTH=837256,CODECS=\"avc1.64001f,mp4a.40.2\",PROGRAM-ID=1,RESOLUTION=854x480,FRAME-RATE=25.000\nhttps://sonydaimenew.akamaized.net/hls/live/2005445/Bliga_FC1005/ENG/hdntl=exp=1778511011~acl=%2f*~id=22255612131139629834187303491070~data=hdntl,2005445,Bliga_FC1005,ENG~hmac=a353b054bdca675af7dc00273b8a322afd7b8a50b4b52001bf4abafe6dff2794/master_600.m3u8?aka_me_session_id=AAAAAAAAAACj7AFqAAAAALWAShFhxbld0iKu%2flMDzaB%2f+x18VXK82%2f82gPnLtsUlMesCnn%2f6DsgYOh0pKE%2fCrSELKMoeRCA7&aka_media_format_type=hls\n#EXT-X-STREAM-INF:BANDWIDTH=1344040,AVERAGE-BANDWIDTH=1344040,CODECS=\"avc1.64001f,mp4a.40.2\",PROGRAM-ID=1,RESOLUTION=960x540,FRAME-RATE=25.000\nhttps://sonydaimenew.akamaized.net/hls/live/2005445/Bliga_FC1005/ENG/hdntl=exp=1778511011~acl=%2f*~id=22255612131139629834187303491070~data=hdntl,2005445,Bliga_FC1005,ENG~hmac=a353b054bdca675af7dc00273b8a322afd7b8a50b4b52001bf4abafe6dff2794/master_1000.m3u8?aka_me_session_id=AAAAAAAAAACj7AFqAAAAALWAShFhxbld0iKu%2flMDzaB%2f+x18VXK82%2f82gPnLtsUlMesCnn%2f6DsgYOh0pKE%2fCrSELKMoeRCA7&aka_media_format_type=hls\n#EXT-X-STREAM-INF:BANDWIDTH=1552456,AVERAGE-BANDWIDTH=1552456,CODECS=\"avc1.640020,mp4a.40.2\",PROGRAM-ID=1,RESOLUTION=1280x720,FRAME-RATE=25.000\nhttps://sonydaimenew.akamaized.net/hls/live/2005445/Bliga_FC1005/ENG/hdntl=exp=1778511011~acl=%2f*~id=22255612131139629834187303491070~data=hdntl,2005445,Bliga_FC1005,ENG~hmac=a353b054bdca675af7dc00273b8a322afd7b8a50b4b52001bf4abafe6dff2794/master_1300.m3u8?aka_me_session_id=AAAAAAAAAACj7AFqAAAAALWAShFhxbld0iKu%2flMDzaB%2f+x18VXK82%2f82gPnLtsUlMesCnn%2f6DsgYOh0pKE%2fCrSELKMoeRCA7&aka_media_format_type=hls\n#EXT-X-STREAM-INF:BANDWIDTH=2365768,AVERAGE-BANDWIDTH=2365768,CODECS=\"avc1.640020,mp4a.40.2\",PROGRAM-ID=1,RESOLUTION=1280x720,FRAME-RATE=25.000\nhttps://sonydaimenew.akamaized.net/hls/live/2005445/Bliga_FC1005/ENG/hdntl=exp=1778511011~acl=%2f*~id=22255612131139629834187303491070~data=hdntl,2005445,Bliga_FC1005,ENG~hmac=a353b054bdca675af7dc00273b8a322afd7b8a50b4b52001bf4abafe6dff2794/master_2000.m3u8?aka_me_session_id=AAAAAAAAAACj7AFqAAAAALWAShFhxbld0iKu%2flMDzaB%2f+x18VXK82%2f82gPnLtsUlMesCnn%2f6DsgYOh0pKE%2fCrSELKMoeRCA7&aka_media_format_type=hls\n#EXT-X-STREAM-INF:BANDWIDTH=2365768,AVERAGE-BANDWIDTH=2365768,CODECS=\"avc1.64002a,mp4a.40.2\",PROGRAM-ID=1,RESOLUTION=1920x1080,FRAME-RATE=25.000\nhttps://sonydaimenew.akamaized.net/hls/live/2005445/Bliga_FC1005/ENG/hdntl=exp=1778511011~acl=%2f*~id=22255612131139629834187303491070~data=hdntl,2005445,Bliga_FC1005,ENG~hmac=a353b054bdca675af7dc00273b8a322afd7b8a50b4b52001bf4abafe6dff2794/master_2200.m3u8?aka_me_session_id=AAAAAAAAAACj7AFqAAAAALWAShFhxbld0iKu%2flMDzaB%2f+x18VXK82%2f82gPnLtsUlMesCnn%2f6DsgYOh0pKE%2fCrSELKMoeRCA7&aka_media_format_type=hls\n#EXT-X-STREAM-INF:BANDWIDTH=3591848,AVERAGE-BANDWIDTH=3591848,CODECS=\"avc1.64002a,mp4a.40.2\",PROGRAM-ID=1,RESOLUTION=1920x1080,FRAME-RATE=25.000\nhttps://sonydaimenew.akamaized.net/hls/live/2005445/Bliga_FC1005/ENG/hdntl=exp=1778511011~acl=%2f*~id=22255612131139629834187303491070~data=hdntl,2005445,Bliga_FC1005,ENG~hmac=a353b054bdca675af7dc00273b8a322afd7b8a50b4b52001bf4abafe6dff2794/master_3200.m3u8?aka_me_session_id=AAAAAAAAAACj7AFqAAAAALWAShFhxbld0iKu%2flMDzaB%2f+x18VXK82%2f82gPnLtsUlMesCnn%2f6DsgYOh0pKE%2fCrSELKMoeRCA7&aka_media_format_type=hls\n#EXT-X-STREAM-INF:BANDWIDTH=4963232,AVERAGE-BANDWIDTH=4963232,CODECS=\"avc1.64002a,mp4a.40.2\",PROGRAM-ID=1,RESOLUTION=1920x1080,FRAME-RATE=50.000\nhttps://sonydaimenew.akamaized.net/hls/live/2005445/Bliga_FC1005/ENG/hdntl=exp=1778511011~acl=%2f*~id=22255612131139629834187303491070~data=hdntl,2005445,Bliga_FC1005,ENG~hmac=a353b054bdca675af7dc00273b8a322afd7b8a50b4b52001bf4abafe6dff2794/master_4500.m3u8?aka_me_session_id=AAAAAAAAAACj7AFqAAAAALWAShFhxbld0iKu%2flMDzaB%2f+x18VXK82%2f82gPnLtsUlMesCnn%2f6DsgYOh0pKE%2fCrSELKMoeRCA7&aka_media_format_type=hls",
              "date": "Sunday 10th of May 2026 08:20:09 PM"
            }
          }
        }
      ]
    },
    {
      "contentId": 1090530048,
      "video_info": {
        "title": "DP World Tour",
        "shortDescription": "Watch all the action from Estrella Damm Catalunya Championship Day 4, LIVE on Sony LIV.",
        "longDescription": "Watch all the action from Estrella Damm Catalunya Championship Day 4, LIVE on Sony LIV.",
        "genres": [
          "Golf"
        ],
        "episodeTitle": " Estrella Damm Catalunya Championship - Day 4 - 10 May 2026"
      },
      "stream_info": {
        "Maximum_Video_Quality": "SDR",
        "dai_asset_key": "https://dai.google.com/ssai/event/1jne4j1lSJeB2tX-a-2TEA/master.m3u8",
        "broadcast_channel": "LIV",
        "audio_language_list": [
          {
            "lang_code": "ENG",
            "lang_label": "English"
          }
        ],
        "emfAttributes__audio_languages": "ENG",
        "platformVariants": {
          "assetType": "MASTER",
          "assetName": "VOD_FULL_HD",
          "videoType": "FULL_HD",
          "audioLanguages": [
            {
              "audioId": 1,
              "audioLanguageName": "ENG",
              "isPreferred": true,
              "audioLanguageLabel": "English"
            }
          ],
          "subtitlesLanguages": [],
          "videoUrl": "NA"
        }
      },
      "air_dates": {
        "contractStartDate": "10 May 2026, 04:00 PM",
        "contractEndDate": "11 May 2026, 01:30 AM",
        "originalAirDate": "10 May 2026, 04:30 PM"
      },
      "image_cdn": {
        "portrait_thumb": "https://origin-staticv2.sonyliv.com/videoasset_images/manage_file/1000017689/177774695430239_DP_World_Estrella_Damm_Day4_portrait_thumb.jpg",
        "thumbnail": "https://origin-staticv2.sonyliv.com/videoasset_images/manage_file/1000017689/177774702026039_DP_World_Estrella_Damm_Day4_landscape_thumb.jpg",
        "masthead_mobile_v1": null,
        "masthead_mobile_v2": null,
        "masthead_logo": "https://origin-staticv2.sonyliv.com/videoasset_images/manage_file/1000000507/1742306648095993_EuropeanQualifiers2025_GENERIC_Masthead_logo_LIVE.png",
        "circular_image": null,
        "image_600x900_clean": null,
        "landscape_thumb": "https://origin-staticv2.sonyliv.com/videoasset_images/manage_file/1000017689/177774702026039_DP_World_Estrella_Damm_Day4_landscape_thumb.jpg"
      },
      "MULTIPLE_AUDIO_LINKS": [
        {
          "LANGUAGE": "English",
          "LANG_CODE": "ENG",
          "DATA": {
            "JITENDRAUNATTI": {
              "Device_Type": "LITE",
              "message": "success",
              "Playback_videoURL": "https://sonydaimenew.akamaized.net/hls/live/20000299/Cataluny1005/ENG/master.m3u8",
              "WIDEVINE": null,
              "STREAMING_TYPE": true,
              "audioLanguages": [
                {
                  "audioLanguageName": "ENG",
                  "audioLanguageLabel": "English"
                }
              ],
              "dai_asset_key": "https://dai.google.com/ssai/event/KqsXcdR0Ta2-bgmQzgV55A/master.m3u8",
              "Maximum_Video_Quality": "SDR",
              "Maximum_Resolution": "FULL_HD",
              "trailer_url": "",
              "systemTime": 1778424614955,
              "DOCTOR_STRANGE": 1778424612,
              "additionalDataJson": {
                "adServer": "GAM",
                "ad_stack": "DAI-IMA",
                "audioCodec": "AAC",
                "audio_quality": "STEREO",
                "enc_format": "HLS",
                "fps": 25,
                "isDaiKey": true,
                "partners": [
                  "ALL"
                ],
                "resolution": "HD",
                "videoCodec": "H264",
                "video_quality": "SDR"
              },
              "Status_code": 200,
              "content_type": "application/json; charset=utf-8",
              "auto_streams": "#EXTM3U\n#EXT-X-VERSION:3\n#EXT-X-STREAM-INF:BANDWIDTH=428552,AVERAGE-BANDWIDTH=428552,CODECS=\"avc1.42e015,mp4a.40.2\",PROGRAM-ID=1,RESOLUTION=426x240,FRAME-RATE=25.000\nhttps://sonydaimenew.akamaized.net/hls/live/20000299/Cataluny1005/ENG/hdntl=exp=1778511015~acl=%2f*~id=22255612131139629834187303491070~data=hdntl,20000299,Cataluny1005,ENG~hmac=c1c5983106a377cf6eae993a49d198a1d1d7c639fdcf6c686577b02edbe09ff0/master_200.m3u8?aka_me_session_id=AAAAAAAAAACn7AFqAAAAAHlXOE0xTnm4uSoMsCchcCStkJYOewHdhyWHiTBojlouoDwtj+5wCLpf1YfthH2+uj1vMpqvHHZK&aka_media_format_type=hls\n#EXT-X-STREAM-INF:BANDWIDTH=632904,AVERAGE-BANDWIDTH=632904,CODECS=\"avc1.4d401e,mp4a.40.2\",PROGRAM-ID=1,RESOLUTION=640x360,FRAME-RATE=25.000\nhttps://sonydaimenew.akamaized.net/hls/live/20000299/Cataluny1005/ENG/hdntl=exp=1778511015~acl=%2f*~id=22255612131139629834187303491070~data=hdntl,20000299,Cataluny1005,ENG~hmac=c1c5983106a377cf6eae993a49d198a1d1d7c639fdcf6c686577b02edbe09ff0/master_400.m3u8?aka_me_session_id=AAAAAAAAAACn7AFqAAAAAHlXOE0xTnm4uSoMsCchcCStkJYOewHdhyWHiTBojlouoDwtj+5wCLpf1YfthH2+uj1vMpqvHHZK&aka_media_format_type=hls\n#EXT-X-STREAM-INF:BANDWIDTH=833160,AVERAGE-BANDWIDTH=833160,CODECS=\"avc1.4d401e,mp4a.40.2\",PROGRAM-ID=1,RESOLUTION=640x360,FRAME-RATE=25.000\nhttps://sonydaimenew.akamaized.net/hls/live/20000299/Cataluny1005/ENG/hdntl=exp=1778511015~acl=%2f*~id=22255612131139629834187303491070~data=hdntl,20000299,Cataluny1005,ENG~hmac=c1c5983106a377cf6eae993a49d198a1d1d7c639fdcf6c686577b02edbe09ff0/master_500.m3u8?aka_me_session_id=AAAAAAAAAACn7AFqAAAAAHlXOE0xTnm4uSoMsCchcCStkJYOewHdhyWHiTBojlouoDwtj+5wCLpf1YfthH2+uj1vMpqvHHZK&aka_media_format_type=hls\n#EXT-X-STREAM-INF:BANDWIDTH=837256,AVERAGE-BANDWIDTH=837256,CODECS=\"avc1.64001f,mp4a.40.2\",PROGRAM-ID=1,RESOLUTION=854x480,FRAME-RATE=25.000\nhttps://sonydaimenew.akamaized.net/hls/live/20000299/Cataluny1005/ENG/hdntl=exp=1778511015~acl=%2f*~id=22255612131139629834187303491070~data=hdntl,20000299,Cataluny1005,ENG~hmac=c1c5983106a377cf6eae993a49d198a1d1d7c639fdcf6c686577b02edbe09ff0/master_600.m3u8?aka_me_session_id=AAAAAAAAAACn7AFqAAAAAHlXOE0xTnm4uSoMsCchcCStkJYOewHdhyWHiTBojlouoDwtj+5wCLpf1YfthH2+uj1vMpqvHHZK&aka_media_format_type=hls\n#EXT-X-STREAM-INF:BANDWIDTH=1344040,AVERAGE-BANDWIDTH=1344040,CODECS=\"avc1.64001f,mp4a.40.2\",PROGRAM-ID=1,RESOLUTION=960x540,FRAME-RATE=25.000\nhttps://sonydaimenew.akamaized.net/hls/live/20000299/Cataluny1005/ENG/hdntl=exp=1778511015~acl=%2f*~id=22255612131139629834187303491070~data=hdntl,20000299,Cataluny1005,ENG~hmac=c1c5983106a377cf6eae993a49d198a1d1d7c639fdcf6c686577b02edbe09ff0/master_1000.m3u8?aka_me_session_id=AAAAAAAAAACn7AFqAAAAAHlXOE0xTnm4uSoMsCchcCStkJYOewHdhyWHiTBojlouoDwtj+5wCLpf1YfthH2+uj1vMpqvHHZK&aka_media_format_type=hls\n#EXT-X-STREAM-INF:BANDWIDTH=1552456,AVERAGE-BANDWIDTH=1552456,CODECS=\"avc1.640020,mp4a.40.2\",PROGRAM-ID=1,RESOLUTION=1280x720,FRAME-RATE=25.000\nhttps://sonydaimenew.akamaized.net/hls/live/20000299/Cataluny1005/ENG/hdntl=exp=1778511015~acl=%2f*~id=22255612131139629834187303491070~data=hdntl,20000299,Cataluny1005,ENG~hmac=c1c5983106a377cf6eae993a49d198a1d1d7c639fdcf6c686577b02edbe09ff0/master_1300.m3u8?aka_me_session_id=AAAAAAAAAACn7AFqAAAAAHlXOE0xTnm4uSoMsCchcCStkJYOewHdhyWHiTBojlouoDwtj+5wCLpf1YfthH2+uj1vMpqvHHZK&aka_media_format_type=hls\n#EXT-X-STREAM-INF:BANDWIDTH=2365768,AVERAGE-BANDWIDTH=2365768,CODECS=\"avc1.640020,mp4a.40.2\",PROGRAM-ID=1,RESOLUTION=1280x720,FRAME-RATE=25.000\nhttps://sonydaimenew.akamaized.net/hls/live/20000299/Cataluny1005/ENG/hdntl=exp=1778511015~acl=%2f*~id=22255612131139629834187303491070~data=hdntl,20000299,Cataluny1005,ENG~hmac=c1c5983106a377cf6eae993a49d198a1d1d7c639fdcf6c686577b02edbe09ff0/master_2000.m3u8?aka_me_session_id=AAAAAAAAAACn7AFqAAAAAHlXOE0xTnm4uSoMsCchcCStkJYOewHdhyWHiTBojlouoDwtj+5wCLpf1YfthH2+uj1vMpqvHHZK&aka_media_format_type=hls\n#EXT-X-STREAM-INF:BANDWIDTH=2365768,AVERAGE-BANDWIDTH=2365768,CODECS=\"avc1.64002a,mp4a.40.2\",PROGRAM-ID=1,RESOLUTION=1920x1080,FRAME-RATE=25.000\nhttps://sonydaimenew.akamaized.net/hls/live/20000299/Cataluny1005/ENG/hdntl=exp=1778511015~acl=%2f*~id=22255612131139629834187303491070~data=hdntl,20000299,Cataluny1005,ENG~hmac=c1c5983106a377cf6eae993a49d198a1d1d7c639fdcf6c686577b02edbe09ff0/master_2200.m3u8?aka_me_session_id=AAAAAAAAAACn7AFqAAAAAHlXOE0xTnm4uSoMsCchcCStkJYOewHdhyWHiTBojlouoDwtj+5wCLpf1YfthH2+uj1vMpqvHHZK&aka_media_format_type=hls\n#EXT-X-STREAM-INF:BANDWIDTH=3591848,AVERAGE-BANDWIDTH=3591848,CODECS=\"avc1.64002a,mp4a.40.2\",PROGRAM-ID=1,RESOLUTION=1920x1080,FRAME-RATE=25.000\nhttps://sonydaimenew.akamaized.net/hls/live/20000299/Cataluny1005/ENG/hdntl=exp=1778511015~acl=%2f*~id=22255612131139629834187303491070~data=hdntl,20000299,Cataluny1005,ENG~hmac=c1c5983106a377cf6eae993a49d198a1d1d7c639fdcf6c686577b02edbe09ff0/master_3200.m3u8?aka_me_session_id=AAAAAAAAAACn7AFqAAAAAHlXOE0xTnm4uSoMsCchcCStkJYOewHdhyWHiTBojlouoDwtj+5wCLpf1YfthH2+uj1vMpqvHHZK&aka_media_format_type=hls\n#EXT-X-STREAM-INF:BANDWIDTH=4963232,AVERAGE-BANDWIDTH=4963232,CODECS=\"avc1.64002a,mp4a.40.2\",PROGRAM-ID=1,RESOLUTION=1920x1080,FRAME-RATE=50.000\nhttps://sonydaimenew.akamaized.net/hls/live/20000299/Cataluny1005/ENG/hdntl=exp=1778511015~acl=%2f*~id=22255612131139629834187303491070~data=hdntl,20000299,Cataluny1005,ENG~hmac=c1c5983106a377cf6eae993a49d198a1d1d7c639fdcf6c686577b02edbe09ff0/master_4500.m3u8?aka_me_session_id=AAAAAAAAAACn7AFqAAAAAHlXOE0xTnm4uSoMsCchcCStkJYOewHdhyWHiTBojlouoDwtj+5wCLpf1YfthH2+uj1vMpqvHHZK&aka_media_format_type=hls",
              "date": "Sunday 10th of May 2026 08:20:12 PM"
            }
          }
        }
      ]
    }
  ],
  "upcoming": [
    {
      "contentId": 1090529981,
      "video_info": {
        "title": "Gullak",
        "shortDescription": "India’s most loved slice-of-life show, Gullak, returns with Season 5! Watch Gullak Season 5, Streaming Soon, on Sony LIV. ",
        "longDescription": "India’s most loved slice-of-life show, Gullak, returns with Season 5! Watch Gullak Season 5, Streaming Soon, on Sony LIV. ",
        "genres": [
          "Comedy",
          "Drama"
        ],
        "episodeTitle": ""
      },
      "stream_info": {
        "Maximum_Video_Quality": "SDR",
        "dai_asset_key": null,
        "broadcast_channel": "LIV",
        "audio_language_list": [
          {
            "lang_code": "HIN",
            "lang_label": "Hindi"
          }
        ],
        "emfAttributes__audio_languages": "HIN",
        "platformVariants": {
          "assetType": "MASTER",
          "assetName": "VOD_FULL_HD1",
          "videoType": "FULL_HD1",
          "audioLanguages": [
            {
              "audioId": 1,
              "audioLanguageName": "HIN",
              "isPreferred": true,
              "audioLanguageLabel": "Hindi",
              "type": "main"
            }
          ],
          "subtitlesLanguages": [],
          "videoUrl": "NA",
          "trailerUrl": "https://streaming.sonyliv.com/trailer/DASH/4148c7810f284c57bd488324ec6e6371/1778212971/baseline-std-v4/GULLAKS5_ANNU_INTRO_PROMO_48SEC_HOR_WSUB_WOBUG_STREAMINGSOON_APP_IND_hin_baseline-800300010.mpd",
          "hasTrailer": true
        }
      },
      "air_dates": {
        "contractStartDate": "08 May 2026, 10:00 AM",
        "contractEndDate": "29 Oct 2028, 11:59 PM",
        "originalAirDate": null
      },
      "image_cdn": {
        "portrait_thumb": "https://origin-staticv2.sonyliv.com/videoasset_images/manage_file/1000017853/1778221276449251_gullak5_streaming_soon_8may_big_portrait_thumb.jpg",
        "thumbnail": "https://origin-staticv2.sonyliv.com/videoasset_images/manage_file/1000017834/177817058069158_GULLAK5_Landscape_Thumb_Dated.jpg",
        "masthead_mobile_v1": "https://origin-staticv2.sonyliv.com/videoasset_images/manage_file/1000002133/1746422754170585_Gullak_5may_masthead_mobile_v1.jpg",
        "masthead_mobile_v2": "https://origin-staticv2.sonyliv.com/videoasset_images/manage_file/1000017834/177817058076858_GULLAK5_masthead_mobile_v2_984x1182.jpg",
        "masthead_logo": "https://origin-staticv2.sonyliv.com/videoasset_images/manage_file/1000017834/177817058070758_GULLAK5_Masthead_Logo_Dated.png",
        "circular_image": null,
        "image_600x900_clean": null,
        "landscape_thumb": "https://origin-staticv2.sonyliv.com/videoasset_images/manage_file/1000017834/177817058069158_GULLAK5_Landscape_Thumb_Dated.jpg"
      },
      "MULTIPLE_AUDIO_LINKS": []
    },
    {
      "contentId": 1090530096,
      "video_info": {
        "title": "The Emirates FA Cup 2025-26 Final",
        "shortDescription": "Tune in to catch all the action from the Emirates FA Cup Finals, exclusively on Sony LIV.",
        "longDescription": "Tune in to catch all the action from the Emirates FA Cup Finals, exclusively on Sony LIV.",
        "genres": [
          "Football"
        ],
        "episodeTitle": ""
      },
      "stream_info": {
        "Maximum_Video_Quality": "SDR",
        "dai_asset_key": null,
        "broadcast_channel": "Sony Sports Ten 5",
        "audio_language_list": [
          {
            "lang_code": "ENG",
            "lang_label": "English"
          }
        ],
        "emfAttributes__audio_languages": "ENG",
        "platformVariants": {
          "assetType": "MASTER",
          "assetName": "VOD_FULL_HD1",
          "videoType": "FULL_HD1",
          "audioLanguages": [
            {
              "audioId": 1,
              "audioLanguageName": "ENG",
              "isPreferred": true,
              "audioLanguageLabel": "English",
              "type": "main"
            }
          ],
          "subtitlesLanguages": [],
          "videoUrl": "NA",
          "trailerUrl": "https://streaming.sonyliv.com/trailer/DASH/a9c542b2709c49f999cea3d32a881baa/1778403614/baseline-std-v4/1090530094_10052026_eng_baseline-800300010.mpd",
          "hasTrailer": true
        }
      },
      "air_dates": {
        "contractStartDate": "10 May 2026, 11:30 AM",
        "contractEndDate": "16 May 2026, 06:00 PM",
        "originalAirDate": null
      },
      "image_cdn": {
        "portrait_thumb": "https://origin-staticv2.sonyliv.com/videoasset_images/manage_file/1000017904/1778397043966633_FACUP26_FINAL_Chelsea_vs_man_city_10MAY_DATED_big_portrait_thumb.jpg",
        "thumbnail": "https://origin-staticv2.sonyliv.com/videoasset_images/manage_file/1000017903/1778396196787448_FACUP26_FINAL_Chelsea_vs_man_city_10MAY_DATED_landscape_thumb.jpg",
        "masthead_mobile_v1": null,
        "masthead_mobile_v2": "https://origin-staticv2.sonyliv.com/videoasset_images/manage_file/1000017901/1778373396000205_FA_Cup_2026_Match_FINAL_masthead_mobile_v2_984x1182_Man_City_vs_Chelsea.jpg",
        "masthead_logo": "https://origin-staticv2.sonyliv.com/videoasset_images/manage_file/1000017901/1778373396000205_FA_Cup_2026_Match_FINAL_Masthead_logo_Man_City_vs_Chelsea_Dated.png",
        "circular_image": null,
        "image_600x900_clean": null,
        "landscape_thumb": "https://origin-staticv2.sonyliv.com/videoasset_images/manage_file/1000017903/1778396196787448_FACUP26_FINAL_Chelsea_vs_man_city_10MAY_DATED_landscape_thumb.jpg"
      },
      "MULTIPLE_AUDIO_LINKS": []
    },
    {
      "contentId": 1090529754,
      "video_info": {
        "title": "Upcoming - Roland-Garros 2026",
        "shortDescription": "Watch all the action from Roland-Garros 2025, only on Sony LIV.",
        "longDescription": "Watch all the action from Roland-Garros 2025, only on Sony LIV.",
        "genres": [
          "Tennis"
        ],
        "episodeTitle": ""
      },
      "stream_info": {
        "Maximum_Video_Quality": "SDR",
        "dai_asset_key": null,
        "broadcast_channel": "Sony Sports Ten 5",
        "audio_language_list": [
          {
            "lang_code": "ENG",
            "lang_label": "English"
          }
        ],
        "emfAttributes__audio_languages": "ENG",
        "platformVariants": {
          "assetType": "MASTER",
          "assetName": "VOD_FULL_HD1",
          "videoType": "FULL_HD1",
          "audioLanguages": [
            {
              "audioId": 1,
              "audioLanguageName": "ENG",
              "isPreferred": true,
              "audioLanguageLabel": "English",
              "type": "main"
            }
          ],
          "subtitlesLanguages": [],
          "videoUrl": "NA",
          "trailerUrl": "https://streaming.sonyliv.com/trailer/DASH/79d2112f51914a80a53770df0749a7a4/1778347438/baseline-std-v4/PROMO_ROLAND_GARROS_INTL_45_SEC_HOR_WOSUB_WOBUG_DATED_APP_eng_baseline-800300010.mpd",
          "hasTrailer": true
        }
      },
      "air_dates": {
        "contractStartDate": "04 May 2026, 07:00 PM",
        "contractEndDate": "07 Jun 2026, 11:55 PM",
        "originalAirDate": null
      },
      "image_cdn": {
        "portrait_thumb": "https://origin-staticv2.sonyliv.com/videoasset_images/manage_file/1000017735/1777915398349912_Rg26_dated_promo_big_portrait_thumb.jpg",
        "thumbnail": "https://origin-staticv2.sonyliv.com/videoasset_images/manage_file/1000017735/1777915577871912_Rg26_dated_promo_landscape_thumb.jpg",
        "masthead_mobile_v1": null,
        "masthead_mobile_v2": null,
        "masthead_logo": null,
        "circular_image": null,
        "image_600x900_clean": null,
        "landscape_thumb": "https://origin-staticv2.sonyliv.com/videoasset_images/manage_file/1000017735/1777915577871912_Rg26_dated_promo_landscape_thumb.jpg"
      },
      "MULTIPLE_AUDIO_LINKS": []
    },
    {
      "contentId": 1090529735,
      "video_info": {
        "title": "Upcoming - India Women's Tour of England 2026",
        "shortDescription": "Tune in to catch all the action from India Women's Tour of England 2026, only on Sony LIV.",
        "longDescription": "Tune in to catch all the action from India Women's Tour of England 2026, only on Sony LIV.",
        "genres": [
          "Cricket"
        ],
        "episodeTitle": ""
      },
      "stream_info": {
        "Maximum_Video_Quality": "SDR",
        "dai_asset_key": null,
        "broadcast_channel": "Sony Sports Ten 5",
        "audio_language_list": [
          {
            "lang_code": "ENG",
            "lang_label": "English"
          }
        ],
        "emfAttributes__audio_languages": "ENG",
        "platformVariants": {
          "assetType": "MASTER",
          "assetName": "VOD_FULL_HD1",
          "videoType": "FULL_HD1",
          "audioLanguages": [
            {
              "audioId": 1,
              "audioLanguageName": "ENG",
              "isPreferred": true,
              "audioLanguageLabel": "English",
              "type": "main"
            }
          ],
          "subtitlesLanguages": [],
          "videoUrl": "NA",
          "trailerUrl": "https://streaming.sonyliv.com/trailer/DASH/6492897d44bc474f8bf7b5511a383450/1777558061/baseline-std-v4/END_VS_IND_WOMENS_30SEC_HOR_DATED_APP_eng_baseline-800300010.mpd",
          "hasTrailer": true
        }
      },
      "air_dates": {
        "contractStartDate": "04 May 2026, 05:00 PM",
        "contractEndDate": "31 Dec 2028, 11:59 PM",
        "originalAirDate": null
      },
      "image_cdn": {
        "portrait_thumb": "https://origin-staticv2.sonyliv.com/videoasset_images/manage_file/1000017721/1777894512161511_ENGvsIND_womend_dated_promo_Big_portrait_thumb.jpg",
        "thumbnail": "https://origin-staticv2.sonyliv.com/videoasset_images/manage_file/1000017721/1777893967612511_ENGvsIND_womend_dated_promo_landscape_thumb.jpg",
        "masthead_mobile_v1": null,
        "masthead_mobile_v2": null,
        "masthead_logo": null,
        "circular_image": null,
        "image_600x900_clean": null,
        "landscape_thumb": "https://origin-staticv2.sonyliv.com/videoasset_images/manage_file/1000017721/1777893967612511_ENGvsIND_womend_dated_promo_landscape_thumb.jpg"
      },
      "MULTIPLE_AUDIO_LINKS": []
    },
    {
      "contentId": 1090530008,
      "video_info": {
        "title": "The Rohit Sharma Show",
        "shortDescription": "Get ready to see a whole new side of the Hitman! Streaming Soon, on Sony LIV.",
        "longDescription": "Get ready to see a whole new side of the Hitman! Streaming Soon, on Sony LIV.",
        "genres": [
          "Reality"
        ],
        "episodeTitle": ""
      },
      "stream_info": {
        "Maximum_Video_Quality": "SDR",
        "dai_asset_key": null,
        "broadcast_channel": "SET",
        "audio_language_list": [
          {
            "lang_code": "HIN",
            "lang_label": "Hindi"
          }
        ],
        "emfAttributes__audio_languages": "HIN",
        "platformVariants": {
          "assetType": "MASTER",
          "assetName": "VOD_FULL_HD1",
          "videoType": "FULL_HD1",
          "audioLanguages": [
            {
              "audioId": 1,
              "audioLanguageName": "HIN",
              "isPreferred": true,
              "audioLanguageLabel": "Hindi",
              "type": "main"
            }
          ],
          "subtitlesLanguages": [],
          "videoUrl": "NA",
          "trailerUrl": "https://streaming.sonyliv.com/trailer/DASH/689b2c36bd684122986cd087920bd376/1778234926/baseline-std-v4/ROHIT_SHARMA_GARDEN_100_SEC_HOR_WOSUB_WOBUG_CS_APP_IND_hin_baseline-800300010.mpd",
          "hasTrailer": true
        }
      },
      "air_dates": {
        "contractStartDate": "08 May 2026, 06:00 PM",
        "contractEndDate": "23 Jun 2121, 11:59 PM",
        "originalAirDate": null
      },
      "image_cdn": {
        "portrait_thumb": "https://origin-staticv2.sonyliv.com/videoasset_images/manage_file/1000017873/1778247055953843_rohit_sharma_show_8may_big_portrait_thumb.jpg",
        "thumbnail": "https://origin-staticv2.sonyliv.com/videoasset_images/manage_file/1000017867/1778222640000459_RS_Landscape_Thumb.jpg",
        "masthead_mobile_v1": null,
        "masthead_mobile_v2": "https://origin-staticv2.sonyliv.com/videoasset_images/manage_file/1000017867/1778222640000459_RS_masthead_mobile_v2_984x1182.jpg",
        "masthead_logo": "https://origin-staticv2.sonyliv.com/videoasset_images/manage_file/1000017867/1778222640000459_RS_Masthead_Logo.png",
        "circular_image": "https://origin-staticv2.sonyliv.com/videoasset_images/manage_file/1000017867/1778222640000459_RS_Circular_Image.jpg",
        "image_600x900_clean": "https://origin-staticv2.sonyliv.com/videoasset_images/manage_file/1000017867/1778222640000459_RS_600x900_clean_Airtel_Portrait.jpg",
        "landscape_thumb": "https://origin-staticv2.sonyliv.com/videoasset_images/manage_file/1000017867/1778222640000459_RS_Landscape_Thumb.jpg"
      },
      "MULTIPLE_AUDIO_LINKS": []
    },
    {
      "contentId": 1090507833,
      "video_info": {
        "title": "India's Best Dancer",
        "shortDescription": "India's Best Dancer Season 5 is coming back with Karisma Kapoor. Watch India's Best Dancer, streaming soon, on Sony LIV. ",
        "longDescription": "India's Best Dancer Season 5 is coming back with Karisma Kapoor. Watch India's Best Dancer, streaming soon, on Sony LIV. ",
        "genres": [
          "Reality",
          "Dance"
        ],
        "episodeTitle": ""
      },
      "stream_info": {
        "Maximum_Video_Quality": "SDR",
        "dai_asset_key": null,
        "broadcast_channel": "SET",
        "audio_language_list": [
          {
            "lang_code": "HIN",
            "lang_label": "Hindi"
          }
        ],
        "emfAttributes__audio_languages": "HIN",
        "platformVariants": {
          "assetType": "MASTER",
          "assetName": "VOD_FULL_HD1",
          "videoType": "FULL_HD1",
          "audioLanguages": [
            {
              "audioId": 1,
              "audioLanguageName": "HIN",
              "isPreferred": true,
              "audioLanguageLabel": "Hindi",
              "type": "main"
            }
          ],
          "subtitlesLanguages": [],
          "videoUrl": "NA",
          "trailerUrl": "https://streaming.sonyliv.com/trailer/DASH/de1442d00fbb40f585a5ef733c861024/1772195955/baseline-std-v4/IBDS5_KARISHMATEASER_TANTANTARA_20SEC_HOR_WOSUB_WOBUG_CS_LIV_SET_APP_IND_hin_baseline-800300010.mpd",
          "hasTrailer": true
        }
      },
      "air_dates": {
        "contractStartDate": "27 Feb 2026, 12:00 AM",
        "contractEndDate": "27 Feb 2121, 11:59 PM",
        "originalAirDate": null
      },
      "image_cdn": {
        "portrait_thumb": "https://origin-staticv2.sonyliv.com/videoasset_images/manage_file/1000016652/177463162330519_IBD_S5_27mar_SS_promo_portrait_thumb.jpg",
        "thumbnail": "https://origin-staticv2.sonyliv.com/videoasset_images/manage_file/1000016061/1773238145752831_ibd5_11mar_SS_landscape_thumb.jpg",
        "masthead_mobile_v1": null,
        "masthead_mobile_v2": "https://origin-staticv2.sonyliv.com/videoasset_images/manage_file/1000016061/1773238634930831_ibd5_11mar_masthead_mobile_v2.jpg",
        "masthead_logo": "https://origin-staticv2.sonyliv.com/videoasset_images/manage_file/1000016061/1773238809735831_ibd5_11mar_SS_masthead_logo.png",
        "circular_image": null,
        "image_600x900_clean": null,
        "landscape_thumb": "https://origin-staticv2.sonyliv.com/videoasset_images/manage_file/1000016061/1773238145752831_ibd5_11mar_SS_landscape_thumb.jpg"
      },
      "MULTIPLE_AUDIO_LINKS": []
    },
    {
      "contentId": 1090529068,
      "video_info": {
        "title": "Hastinapur Ke Veer",
        "shortDescription": "Hastinapur Ke Veer unfolds the saga of the five Pandavas brothers, who embody courage, righteousness, and sacrifice as they confront the relentless forces of ambition and injustice. Watch Hastinapur Ke Veer streaming soon, only on Sony LIV. ",
        "longDescription": "Hastinapur Ke Veer unfolds the saga of the five Pandavas brothers, who embody courage, righteousness, and sacrifice as they confront the relentless forces of ambition and injustice. Watch Hastinapur Ke Veer streaming soon, only on Sony LIV. ",
        "genres": [
          "Mythology"
        ],
        "episodeTitle": ""
      },
      "stream_info": {
        "Maximum_Video_Quality": "SDR",
        "dai_asset_key": null,
        "broadcast_channel": "SAB",
        "audio_language_list": [
          {
            "lang_code": "HIN",
            "lang_label": "Hindi"
          }
        ],
        "emfAttributes__audio_languages": "HIN",
        "platformVariants": {
          "assetType": "MASTER",
          "assetName": "VOD_FULL_HD1",
          "videoType": "FULL_HD1",
          "audioLanguages": [
            {
              "audioId": 1,
              "audioLanguageName": "HIN",
              "isPreferred": true,
              "audioLanguageLabel": "Hindi",
              "type": "main"
            }
          ],
          "subtitlesLanguages": [],
          "videoUrl": "NA",
          "trailerUrl": "https://streaming.sonyliv.com/trailer/DASH/11c08ff4d4d34e049dba2b79f7bcf1a6/1777027344/baseline-std-v4/HKV_PROMO01_60SEC_HOR_WOSUB_WOBUG_CS_APP_IND_hin_baseline-800300010.mpd",
          "hasTrailer": true
        }
      },
      "air_dates": {
        "contractStartDate": "24 Apr 2026, 03:00 PM",
        "contractEndDate": "23 Jun 2121, 11:59 PM",
        "originalAirDate": null
      },
      "image_cdn": {
        "portrait_thumb": "https://origin-staticv2.sonyliv.com/videoasset_images/manage_file/1000016652/177462736009719_Hastinapur_Ke_Veer_SS_27mar_portrait_thumb.jpg",
        "thumbnail": "https://origin-staticv2.sonyliv.com/videoasset_images/manage_file/1000016500/1774271039207830_Hastinapur_k_veer_23march_SS_Landscape_Thumb.jpg",
        "masthead_mobile_v1": null,
        "masthead_mobile_v2": "https://origin-staticv2.sonyliv.com/videoasset_images/manage_file/1000016500/1774271001348830_Hastinapur_k_veer_23march_masthead_mobile_v2.jpg",
        "masthead_logo": "https://origin-staticv2.sonyliv.com/videoasset_images/manage_file/1000016500/1774270193031830_Hastinapur_k_veer_23march_SS_masthead_logo.png",
        "circular_image": null,
        "image_600x900_clean": null,
        "landscape_thumb": "https://origin-staticv2.sonyliv.com/videoasset_images/manage_file/1000016500/1774271039207830_Hastinapur_k_veer_23march_SS_Landscape_Thumb.jpg"
      },
      "MULTIPLE_AUDIO_LINKS": []
    },
    {
      "contentId": 1090529564,
      "video_info": {
        "title": "This May Step Into Every Mood",
        "shortDescription": "This May, match every mood with exclusive shows, movies, and live sports content only on Sony LIV.",
        "longDescription": "This May, match every mood with exclusive shows, movies, and live sports content only on Sony LIV.",
        "genres": [
          "Entertainment",
          "Sports"
        ],
        "episodeTitle": ""
      },
      "stream_info": {
        "Maximum_Video_Quality": "SDR",
        "dai_asset_key": null,
        "broadcast_channel": "LIV",
        "audio_language_list": [
          {
            "lang_code": "HIN",
            "lang_label": "Hindi"
          }
        ],
        "emfAttributes__audio_languages": "HIN",
        "platformVariants": {
          "assetType": "MASTER",
          "assetName": "VOD_FULL_HD1",
          "videoType": "FULL_HD1",
          "audioLanguages": [
            {
              "audioId": 1,
              "audioLanguageName": "HIN",
              "isPreferred": true,
              "audioLanguageLabel": "Hindi",
              "type": "main"
            }
          ],
          "subtitlesLanguages": [],
          "videoUrl": "NA",
          "trailerUrl": "https://streaming.sonyliv.com/trailer/DASH/e4e4454b12f04da0bebc00752c3028cd/1777577669/baseline-std-v4/SummerMAY_COMPOSITE_60_SEC_REV_HOR_WOSUB_WOBUG_APP_hin_baseline-800300010.mpd",
          "hasTrailer": true
        }
      },
      "air_dates": {
        "contractStartDate": "01 May 2026, 12:00 AM",
        "contractEndDate": "14 Mar 2121, 11:59 PM",
        "originalAirDate": null
      },
      "image_cdn": {
        "portrait_thumb": "https://origin-staticv2.sonyliv.com/videoasset_images/manage_file/1000017643/1777568944231737_composite_big_portrait_thumb.jpg",
        "thumbnail": "https://origin-staticv2.sonyliv.com/videoasset_images/manage_file/1000017647/1777578078525320_composite_landscape_thumbnail.jpg",
        "masthead_mobile_v1": null,
        "masthead_mobile_v2": null,
        "masthead_logo": null,
        "circular_image": null,
        "image_600x900_clean": null,
        "landscape_thumb": "https://origin-staticv2.sonyliv.com/videoasset_images/manage_file/1000017647/1777578078525320_composite_landscape_thumbnail.jpg"
      },
      "MULTIPLE_AUDIO_LINKS": []
    }
  ]
}